sleapyfaces/__about__.py
sleapyfaces/__init__.py
sleapyfaces/__main__.py
sleapyfaces/config.py
sleapyfaces/docstring.py
sleapyfaces/base/__init__.py
sleapyfaces/base/expr.py
sleapyfaces/base/proj.py
sleapyfaces/base/projs.py
sleapyfaces/base/type.py
sleapyfaces/cli/__init__.py
sleapyfaces/clustering/__init__.py
sleapyfaces/clustering/algorithms.py
sleapyfaces/clustering/features.py
sleapyfaces/files/__init__.py
sleapyfaces/files/events.py
sleapyfaces/files/metadata.py
sleapyfaces/files/sleap.py
sleapyfaces/utils/__init__.py
sleapyfaces/utils/graph.py
sleapyfaces/utils/io.py
sleapyfaces/utils/normalize.py
sleapyfaces/utils/reform.py
sleapyfaces/utils/structs.py
sleapyfaces-1.2.9.post1.dist-info/METADATA
sleapyfaces-1.2.9.post1.dist-info/WHEEL
sleapyfaces-1.2.9.post1.dist-info/licenses/LICENSE
sleapyfaces-1.2.9.post1.dist-info/RECORD
