Metadata-Version: 2.1
Name: sleapyfaces
Version: 1.2.9.post1
Summary: A package for extracting facial expressions from SLEAP analyses
Project-URL: Documentation, https://github.com/annie444/sleapyfaces#readme
Project-URL: Issues, https://github.com/annie444/sleapyfaces/issues
Project-URL: Source, https://github.com/annie444/sleapyfaces
Project-URL: Homepage, https://github.com/annie444/sleapyfaces
Author-email: "Analetta (Annie) Ehler" <annie.ehler.4@gmail.com>
License-Expression: MIT
License-File: LICENSE
Keywords: SLEAP,analysis,classification,extraction,facial data,facial expression,recognition,tracking analyses
Classifier: Development Status :: 3 - Alpha
Classifier: License :: OSI Approved :: MIT License
Classifier: Programming Language :: Python
Classifier: Programming Language :: Python :: 3.7
Classifier: Programming Language :: Python :: 3.8
Classifier: Programming Language :: Python :: 3.9
Classifier: Programming Language :: Python :: 3.10
Classifier: Programming Language :: Python :: 3.11
Classifier: Programming Language :: Python :: Implementation :: CPython
Classifier: Programming Language :: Python :: Implementation :: PyPy
Requires-Python: >=3.7
Requires-Dist: click
Requires-Dist: ffmpeg-python
Requires-Dist: geomstats
Requires-Dist: h5py
Requires-Dist: matplotlib
Requires-Dist: more-itertools
Requires-Dist: numpy
Requires-Dist: pandas
Requires-Dist: pathvalidate
Requires-Dist: plotly
Requires-Dist: pytest
Requires-Dist: pytest-cov
Requires-Dist: python-configuration
Requires-Dist: python-rapidjson
Requires-Dist: scikit-learn
Requires-Dist: scipy
Requires-Dist: seaborn
Requires-Dist: statsmodels
Requires-Dist: tables
